pandocx/__init__.py
pandocx/data_reader.py
pandocx/pandoc.py
pandocx/process.py
pandocx/utils.py
pandocx/data/code.md
pandocx/data/insertTables.lua
pandocx/data/pandoc-ling.lua
pandocx-0.0.1.dist-info/METADATA
pandocx-0.0.1.dist-info/WHEEL
pandocx-0.0.1.dist-info/top_level.txt
pandocx-0.0.1.dist-info/RECORD
